interpolatr/__init__.py
interpolatr/compat.py
interpolatr/config.py
interpolatr/sink.py
interpolatr/util.py
interpolatr-0.0.2.data/scripts/interpolatr
interpolatr-0.0.2.dist-info/DESCRIPTION.rst
interpolatr-0.0.2.dist-info/LICENSE.txt
interpolatr-0.0.2.dist-info/METADATA
interpolatr-0.0.2.dist-info/RECORD
interpolatr-0.0.2.dist-info/WHEEL
interpolatr-0.0.2.dist-info/metadata.json
interpolatr-0.0.2.dist-info/top_level.txt
