Metadata-Version: 2.0
Name: interpolatr
Version: 0.0.2
Summary: Interpolation tool
Home-page: http://github.com/jacobtolar/interpolatr
Author: Jacob Tolar
Author-email: development@sheckel.net
License: Apache 2.0
Platform: UNKNOWN
Classifier: Programming Language :: Python
Classifier: Programming Language :: Python :: 2.7
Requires-Dist: Jinja2 (>=2.8)
Requires-Dist: PyYAML (>=3.12)
Requires-Dist: click (>=6.0)
Requires-Dist: chainmap (>=1.0.2); python_version < '3.0'
